README.md
setup.cfg
setup.py
Spitzer/__init__.py
Spitzer/command.py
Spitzer/exit.py
Spitzer/host.py
Spitzer/interlace.py
Spitzer/main.py
Spitzer/print.py
Spitzer/searchsploit.py
SpitzerSec.egg-info/PKG-INFO
SpitzerSec.egg-info/SOURCES.txt
SpitzerSec.egg-info/dependency_links.txt
SpitzerSec.egg-info/entry_points.txt
SpitzerSec.egg-info/requires.txt
SpitzerSec.egg-info/top_level.txt
Spitzer/chache/__init__.py
Spitzer/chache/chache.py
Spitzer/config/__init__.py
Spitzer/config/config.json
Spitzer/config/config.py
Spitzer/config/data.json
Spitzer/exploiters/__init__.py
Spitzer/exploiters/bruteforce.py
Spitzer/exploiters/exploit.py
Spitzer/exploiters/ftp.py
Spitzer/exploiters/netdisk.py
Spitzer/exploiters/websploit.py
Spitzer/exploiters/web/__init__.py
Spitzer/exploiters/web/burp.py
Spitzer/exploiters/web/dirbuster.py
Spitzer/exploiters/web/headers.py
Spitzer/exploiters/web/screenshot.py
Spitzer/exploiters/web/spider.py
Spitzer/exploiters/web/testssl.py
Spitzer/result/__init__.py
Spitzer/result/export_report.py
Spitzer/result/export_sql.py
Spitzer/result/export_table.py
Spitzer/result/export_text.py
Spitzer/result/result.py
Spitzer/scanner/__init__.py
Spitzer/scanner/masscanner.py
Spitzer/scanner/nmapper.py
Spitzer/scanner/scanner.py
test/__init__.py
test/main_test.py
test/test_config.py
test/test_host.py
test/test_searchsploit.py