Metadata-Version: 2.1
Name: SpitzerSec
Version: 0.1.7
Summary: A scanner for the first day of a pentest
Home-page: UNKNOWN
Author: Rick Theeuwes
License: UNKNOWN
Download-URL: https://github.com/Riqky/Spitzer/archive/0.1.7.tar.gz
Platform: UNKNOWN
